fds/__init__.py
fds/sdk/__init__.py
fds/sdk/MarketIntelligence/__init__.py
fds/sdk/MarketIntelligence/api_client.py
fds/sdk/MarketIntelligence/configuration.py
fds/sdk/MarketIntelligence/exceptions.py
fds/sdk/MarketIntelligence/model_utils.py
fds/sdk/MarketIntelligence/rest.py
fds/sdk/MarketIntelligence/api/__init__.py
fds/sdk/MarketIntelligence/api/create_report_api.py
fds/sdk/MarketIntelligence/api/retrieve_refreshed_data_api.py
fds/sdk/MarketIntelligence/api/retrieve_refreshed_report_api.py
fds/sdk/MarketIntelligence/api/retrieve_report_list_api.py
fds/sdk/MarketIntelligence/apis/__init__.py
fds/sdk/MarketIntelligence/model/__init__.py
fds/sdk/MarketIntelligence/model/fetch_report_poll_id.py
fds/sdk/MarketIntelligence/model/get_report_info.py
fds/sdk/MarketIntelligence/model/miapi_post_request.py
fds/sdk/MarketIntelligence/model/post_request_example.py
fds/sdk/MarketIntelligence/model/post_response_info.py
fds/sdk/MarketIntelligence/model/report_content.py
fds/sdk/MarketIntelligence/model/report_data_header.py
fds/sdk/MarketIntelligence/models/__init__.py
fds.sdk.MarketIntelligence-0.21.14.dist-info/LICENSE
fds.sdk.MarketIntelligence-0.21.14.dist-info/METADATA
fds.sdk.MarketIntelligence-0.21.14.dist-info/WHEEL
fds.sdk.MarketIntelligence-0.21.14.dist-info/top_level.txt
fds.sdk.MarketIntelligence-0.21.14.dist-info/RECORD
